spider_mcp_client/__init__.py
spider_mcp_client/client.py
spider_mcp_client/exceptions.py
spider_mcp_client-0.1.8.dist-info/licenses/LICENSE
spider_mcp_client-0.1.8.dist-info/METADATA
spider_mcp_client-0.1.8.dist-info/WHEEL
spider_mcp_client-0.1.8.dist-info/top_level.txt
spider_mcp_client-0.1.8.dist-info/RECORD
