Metadata-Version: 2.4
Name: spider-mcp-client
Version: 0.1.8
Summary: Official Python client for Spider MCP web scraping API
Home-page: https://github.com/spider-mcp/spider-mcp-client
Author: Spider MCP Team
Author-email: importal <xychen@msn.com>
Maintainer-email: importal <xychen@msn.com>
License: MIT
Project-URL: Homepage, https://github.com/xychenmsn/spider-mcp-client
Project-URL: Documentation, https://github.com/xychenmsn/spider-mcp-client#readme
Project-URL: Repository, https://github.com/xychenmsn/spider-mcp-client
Project-URL: Bug Reports, https://github.com/xychenmsn/spider-mcp-client/issues
Project-URL: Changelog, https://github.com/xychenmsn/spider-mcp-client/blob/main/CHANGELOG.md
Keywords: web scraping,spider,mcp,api client,html parsing,data extraction
Classifier: Development Status :: 4 - Beta
Classifier: Intended Audience :: Developers
Classifier: License :: OSI Approved :: MIT License
Classifier: Operating System :: OS Independent
Classifier: Programming Language :: Python :: 3
Classifier: Programming Language :: Python :: 3.8
Classifier: Programming Language :: Python :: 3.9
Classifier: Programming Language :: Python :: 3.10
Classifier: Programming Language :: Python :: 3.11
Classifier: Programming Language :: Python :: 3.12
Classifier: Topic :: Internet :: WWW/HTTP :: Browsers
Classifier: Topic :: Software Development :: Libraries :: Python Modules
Classifier: Topic :: Text Processing :: Markup :: HTML
Requires-Python: >=3.8
License-File: LICENSE
Requires-Dist: requests>=2.25.0
Requires-Dist: typing-extensions>=4.0.0; python_version < "3.10"
Provides-Extra: dev
Requires-Dist: pytest>=6.0; extra == "dev"
Requires-Dist: pytest-asyncio>=0.18.0; extra == "dev"
Requires-Dist: black>=22.0.0; extra == "dev"
Requires-Dist: flake8>=4.0.0; extra == "dev"
Requires-Dist: mypy>=0.950; extra == "dev"
Requires-Dist: build>=0.8.0; extra == "dev"
Requires-Dist: twine>=4.0.0; extra == "dev"
Provides-Extra: async
Requires-Dist: aiohttp>=3.8.0; extra == "async"
Dynamic: author
Dynamic: home-page
Dynamic: license-file
Dynamic: requires-python
